{
    "name": "MPMB-importer",
    "title": "MPMB Importer",
    "description": "Import your MPMB character sheet to Foundry and match to SRD or other licensed content",
    "author" : "Spetzel",
    "version": "0.5.0",
    "minimumCoreVersion": "0.6.5",
    "compatibleCoreVersion": "0.7.2",
    "languages": [{
        "lang": "en",
        "name": "English",
        "path": "lang/en.json"
    }],
    "esmodules" : ["modules/MPMBImporter.js","modules/Actor5e.js"
    ],
    "styles": ["css/style.css"],
    "dependencies": [
        {
            "name": "dnd5e",
            "type": "system"
        }
    ],
    "system": "dnd5e",
    "readme": "https://github.com/opus1217/MPMB-importer/blob/v0.5.0/README.md",
    "bugs": "https://github.com/opus1217/MPMB-importer/issues",
    "changelog": "https://github.com/opus1217/MPMB-importer/blob/master/CHANGELOG.md",
    "manifest": "https://raw.githubusercontent.com/opus1217/MPMB-importer/v0.5.0/module.json",
    "download": "https://github.com/opus1217/MPMB-importer/archive/v0.5.0.zip",
    "url": "https://github.com/opus1217/MPMB-importer"
}
